tianyancha/__init__.py
tianyancha/apilist.json
tianyancha/client.py
tianyancha/sync.py
tianyancha-0.2.1.dist-info/LICENSE
tianyancha-0.2.1.dist-info/METADATA
tianyancha-0.2.1.dist-info/WHEEL
tianyancha-0.2.1.dist-info/top_level.txt
tianyancha-0.2.1.dist-info/RECORD
