Metadata-Version: 2.1
Name: tianyancha
Version: 0.2.1
Summary: Tianyancha SDK for python, which based on https://open.tianyancha.com/
Home-page: https://github.com/iamsk/tianyancha
Author: Bin
Author-email: iamsk.info@gmail.com
License: MIT
Classifier: License :: OSI Approved :: MIT License
Classifier: Programming Language :: Python
Classifier: Programming Language :: Python :: 3
Classifier: Programming Language :: Python :: 3.6
Classifier: Programming Language :: Python :: Implementation :: CPython
Classifier: Programming Language :: Python :: Implementation :: PyPy
Requires-Python: >=3.6.0
License-File: LICENSE
Requires-Dist: pytest>=3.6.4
Requires-Dist: requests>=2.12.4
Requires-Dist: retry>=0.9.2
Requires-Dist: python-dotenv>=1.0.1
